random_snake.py
random_snake-1.0.0.dist-info/entry_points.txt
random_snake-1.0.0.dist-info/WHEEL
random_snake-1.0.0.dist-info/METADATA
random_snake-1.0.0.dist-info/RECORD
