Metadata-Version: 2.1
Name: random-snake
Version: 1.0.0
Summary: just a random sneaky snake
Author: worldmaker
Author-email: worldmaker18349276@gmail.com
Requires-Python: >=3.8,<4.0
Classifier: Programming Language :: Python :: 3
Classifier: Programming Language :: Python :: 3.10
Classifier: Programming Language :: Python :: 3.8
Classifier: Programming Language :: Python :: 3.9
